{
    "International_number_ID": "7026",
    "Data_lines": "16",
    "International_number_ID_Replicate": "7026",
    "Flag": "0",
    "DurationOfTimeUnit": "6",
    "Name": "RUTH",
    "Date": "19901017",
    "Type": "8",
    "Route": [
        {
            "Time": "1970-11-26T00:00:00",
            "Grade": "2",
            "Latitude": 9.8,
            "Longitude": 113.4,
            "CentralPressure": "1004"
        },
        {
            "Time": "1970-11-26T06:00:00",
            "Grade": "2",
            "Latitude": 9.7,
            "Longitude": 112.3,
            "CentralPressure": "1000"
        },
        {
            "Time": "1970-11-26T12:00:00",
            "Grade": "2",
            "Latitude": 9.5,
            "Longitude": 111.3,
            "CentralPressure": "1000"
        },
        {
            "Time": "1970-11-26T18:00:00",
            "Grade": "2",
            "Latitude": 9.2,
            "Longitude": 110.2,
            "CentralPressure": "1000"
        },
        {
            "Time": "1970-11-27T00:00:00",
            "Grade": "2",
            "Latitude": 8.9,
            "Longitude": 109.2,
            "CentralPressure": "998"
        },
        {
            "Time": "1970-11-27T06:00:00",
            "Grade": "9",
            "Latitude": 8.7,
            "Longitude": 108.2,
            "CentralPressure": "996"
        },
        {
            "Time": "1970-11-27T12:00:00",
            "Grade": "9",
            "Latitude": 8.4,
            "Longitude": 107.1,
            "CentralPressure": "998"
        },
        {
            "Time": "1970-11-27T18:00:00",
            "Grade": "9",
            "Latitude": 8.1,
            "Longitude": 106.1,
            "CentralPressure": "1000"
        },
        {
            "Time": "1970-11-28T00:00:00",
            "Grade": "2",
            "Latitude": 7.9,
            "Longitude": 105.0,
            "CentralPressure": "1002"
        },
        {
            "Time": "1970-11-28T06:00:00",
            "Grade": "2",
            "Latitude": 8.0,
            "Longitude": 104.1,
            "CentralPressure": "1002"
        },
        {
            "Time": "1970-11-28T12:00:00",
            "Grade": "2",
            "Latitude": 7.9,
            "Longitude": 103.2,
            "CentralPressure": "1002"
        },
        {
            "Time": "1970-11-28T18:00:00",
            "Grade": "2",
            "Latitude": 8.0,
            "Longitude": 102.3,
            "CentralPressure": "1004"
        },
        {
            "Time": "1970-11-29T00:00:00",
            "Grade": "2",
            "Latitude": 8.3,
            "Longitude": 101.5,
            "CentralPressure": "1004"
        },
        {
            "Time": "1970-11-29T06:00:00",
            "Grade": "2",
            "Latitude": 8.7,
            "Longitude": 100.7,
            "CentralPressure": "1004"
        },
        {
            "Time": "1970-11-29T12:00:00",
            "Grade": "2",
            "Latitude": 9.3,
            "Longitude": 99.8,
            "CentralPressure": "1002"
        },
        {
            "Time": "1970-11-29T18:00:00",
            "Grade": "2",
            "Latitude": 9.9,
            "Longitude": 99.2,
            "CentralPressure": "1004"
        }
    ],
    "FirstPointDate": "1970-11-26T00:00:00"
}