{
    "International_number_ID": "8523",
    "Data_lines": "31",
    "International_number_ID_Replicate": "8523",
    "Flag": "0",
    "DurationOfTimeUnit": "6",
    "Name": "ELLIS",
    "Date": "19921021",
    "Type": "8",
    "Route": [
        {
            "Time": "1985-10-15T12:00:00",
            "Grade": "2",
            "Latitude": 8.0,
            "Longitude": 155.0,
            "CentralPressure": "1006",
            "Maximum_sustained_wind_speed": "000"
        },
        {
            "Time": "1985-10-15T18:00:00",
            "Grade": "2",
            "Latitude": 9.0,
            "Longitude": 154.0,
            "CentralPressure": "1004",
            "Maximum_sustained_wind_speed": "000"
        },
        {
            "Time": "1985-10-16T00:00:00",
            "Grade": "2",
            "Latitude": 10.0,
            "Longitude": 153.0,
            "CentralPressure": "1004",
            "Maximum_sustained_wind_speed": "000"
        },
        {
            "Time": "1985-10-16T06:00:00",
            "Grade": "3",
            "Latitude": 10.7,
            "Longitude": 152.0,
            "CentralPressure": "1000",
            "Maximum_sustained_wind_speed": "040",
            "Direction_LR50plus": "0",
            "Longest_radius_of_50kt": 0,
            "Shortest_radius_of_50kt": 0,
            "Direction_LR30plus": "9",
            "Longest_radius_of_30kt": 125,
            "Shortest_radius_of_30kt": 125
        },
        {
            "Time": "1985-10-16T12:00:00",
            "Grade": "3",
            "Latitude": 10.7,
            "Longitude": 151.6,
            "CentralPressure": "1000",
            "Maximum_sustained_wind_speed": "040",
            "Direction_LR50plus": "0",
            "Longest_radius_of_50kt": 0,
            "Shortest_radius_of_50kt": 0,
            "Direction_LR30plus": "9",
            "Longest_radius_of_30kt": 125,
            "Shortest_radius_of_30kt": 125
        },
        {
            "Time": "1985-10-16T18:00:00",
            "Grade": "3",
            "Latitude": 10.7,
            "Longitude": 151.2,
            "CentralPressure": "1000",
            "Maximum_sustained_wind_speed": "040",
            "Direction_LR50plus": "0",
            "Longest_radius_of_50kt": 0,
            "Shortest_radius_of_50kt": 0,
            "Direction_LR30plus": "9",
            "Longest_radius_of_30kt": 125,
            "Shortest_radius_of_30kt": 125
        },
        {
            "Time": "1985-10-17T00:00:00",
            "Grade": "3",
            "Latitude": 10.7,
            "Longitude": 150.8,
            "CentralPressure": "1000",
            "Maximum_sustained_wind_speed": "045",
            "Direction_LR50plus": "0",
            "Longest_radius_of_50kt": 0,
            "Shortest_radius_of_50kt": 0,
            "Direction_LR30plus": "9",
            "Longest_radius_of_30kt": 125,
            "Shortest_radius_of_30kt": 125
        },
        {
            "Time": "1985-10-17T06:00:00",
            "Grade": "3",
            "Latitude": 10.7,
            "Longitude": 150.6,
            "CentralPressure": "996",
            "Maximum_sustained_wind_speed": "045",
            "Direction_LR50plus": "0",
            "Longest_radius_of_50kt": 0,
            "Shortest_radius_of_50kt": 0,
            "Direction_LR30plus": "9",
            "Longest_radius_of_30kt": 125,
            "Shortest_radius_of_30kt": 125
        },
        {
            "Time": "1985-10-17T12:00:00",
            "Grade": "3",
            "Latitude": 10.2,
            "Longitude": 150.3,
            "CentralPressure": "996",
            "Maximum_sustained_wind_speed": "045",
            "Direction_LR50plus": "0",
            "Longest_radius_of_50kt": 0,
            "Shortest_radius_of_50kt": 0,
            "Direction_LR30plus": "9",
            "Longest_radius_of_30kt": 125,
            "Shortest_radius_of_30kt": 125
        },
        {
            "Time": "1985-10-17T18:00:00",
            "Grade": "3",
            "Latitude": 9.7,
            "Longitude": 150.1,
            "CentralPressure": "996",
            "Maximum_sustained_wind_speed": "045",
            "Direction_LR50plus": "0",
            "Longest_radius_of_50kt": 0,
            "Shortest_radius_of_50kt": 0,
            "Direction_LR30plus": "9",
            "Longest_radius_of_30kt": 125,
            "Shortest_radius_of_30kt": 125
        },
        {
            "Time": "1985-10-18T00:00:00",
            "Grade": "4",
            "Latitude": 9.3,
            "Longitude": 149.9,
            "CentralPressure": "996",
            "Maximum_sustained_wind_speed": "050",
            "Direction_LR50plus": "0",
            "Longest_radius_of_50kt": 0,
            "Shortest_radius_of_50kt": 0,
            "Direction_LR30plus": "9",
            "Longest_radius_of_30kt": 125,
            "Shortest_radius_of_30kt": 125
        },
        {
            "Time": "1985-10-18T06:00:00",
            "Grade": "4",
            "Latitude": 8.7,
            "Longitude": 149.9,
            "CentralPressure": "996",
            "Maximum_sustained_wind_speed": "050",
            "Direction_LR50plus": "0",
            "Longest_radius_of_50kt": 0,
            "Shortest_radius_of_50kt": 0,
            "Direction_LR30plus": "9",
            "Longest_radius_of_30kt": 125,
            "Shortest_radius_of_30kt": 125
        },
        {
            "Time": "1985-10-18T12:00:00",
            "Grade": "4",
            "Latitude": 8.2,
            "Longitude": 149.4,
            "CentralPressure": "998",
            "Maximum_sustained_wind_speed": "050",
            "Direction_LR50plus": "0",
            "Longest_radius_of_50kt": 0,
            "Shortest_radius_of_50kt": 0,
            "Direction_LR30plus": "9",
            "Longest_radius_of_30kt": 125,
            "Shortest_radius_of_30kt": 125
        },
        {
            "Time": "1985-10-18T18:00:00",
            "Grade": "4",
            "Latitude": 7.7,
            "Longitude": 148.8,
            "CentralPressure": "1000",
            "Maximum_sustained_wind_speed": "050",
            "Direction_LR50plus": "0",
            "Longest_radius_of_50kt": 0,
            "Shortest_radius_of_50kt": 0,
            "Direction_LR30plus": "9",
            "Longest_radius_of_30kt": 125,
            "Shortest_radius_of_30kt": 125
        },
        {
            "Time": "1985-10-19T00:00:00",
            "Grade": "3",
            "Latitude": 7.2,
            "Longitude": 148.3,
            "CentralPressure": "1000",
            "Maximum_sustained_wind_speed": "045",
            "Direction_LR50plus": "0",
            "Longest_radius_of_50kt": 0,
            "Shortest_radius_of_50kt": 0,
            "Direction_LR30plus": "9",
            "Longest_radius_of_30kt": 125,
            "Shortest_radius_of_30kt": 125
        },
        {
            "Time": "1985-10-19T06:00:00",
            "Grade": "3",
            "Latitude": 6.6,
            "Longitude": 148.0,
            "CentralPressure": "1000",
            "Maximum_sustained_wind_speed": "045",
            "Direction_LR50plus": "0",
            "Longest_radius_of_50kt": 0,
            "Shortest_radius_of_50kt": 0,
            "Direction_LR30plus": "9",
            "Longest_radius_of_30kt": 125,
            "Shortest_radius_of_30kt": 125
        },
        {
            "Time": "1985-10-19T12:00:00",
            "Grade": "3",
            "Latitude": 6.3,
            "Longitude": 147.0,
            "CentralPressure": "1002",
            "Maximum_sustained_wind_speed": "040",
            "Direction_LR50plus": "0",
            "Longest_radius_of_50kt": 0,
            "Shortest_radius_of_50kt": 0,
            "Direction_LR30plus": "9",
            "Longest_radius_of_30kt": 100,
            "Shortest_radius_of_30kt": 100
        },
        {
            "Time": "1985-10-19T18:00:00",
            "Grade": "2",
            "Latitude": 6.2,
            "Longitude": 146.1,
            "CentralPressure": "1004",
            "Maximum_sustained_wind_speed": "000"
        },
        {
            "Time": "1985-10-20T00:00:00",
            "Grade": "2",
            "Latitude": 6.3,
            "Longitude": 145.1,
            "CentralPressure": "1006",
            "Maximum_sustained_wind_speed": "000"
        },
        {
            "Time": "1985-10-20T06:00:00",
            "Grade": "2",
            "Latitude": 7.0,
            "Longitude": 144.0,
            "CentralPressure": "1006",
            "Maximum_sustained_wind_speed": "000"
        },
        {
            "Time": "1985-10-20T12:00:00",
            "Grade": "2",
            "Latitude": 8.0,
            "Longitude": 143.5,
            "CentralPressure": "1006",
            "Maximum_sustained_wind_speed": "000"
        },
        {
            "Time": "1985-10-20T18:00:00",
            "Grade": "2",
            "Latitude": 8.5,
            "Longitude": 142.0,
            "CentralPressure": "1006",
            "Maximum_sustained_wind_speed": "000"
        },
        {
            "Time": "1985-10-21T00:00:00",
            "Grade": "2",
            "Latitude": 9.0,
            "Longitude": 140.0,
            "CentralPressure": "1006",
            "Maximum_sustained_wind_speed": "000"
        },
        {
            "Time": "1985-10-21T06:00:00",
            "Grade": "2",
            "Latitude": 9.5,
            "Longitude": 138.0,
            "CentralPressure": "1006",
            "Maximum_sustained_wind_speed": "000"
        },
        {
            "Time": "1985-10-21T12:00:00",
            "Grade": "2",
            "Latitude": 10.5,
            "Longitude": 137.0,
            "CentralPressure": "1006",
            "Maximum_sustained_wind_speed": "000"
        },
        {
            "Time": "1985-10-21T18:00:00",
            "Grade": "2",
            "Latitude": 11.0,
            "Longitude": 136.0,
            "CentralPressure": "1006",
            "Maximum_sustained_wind_speed": "000"
        },
        {
            "Time": "1985-10-22T00:00:00",
            "Grade": "2",
            "Latitude": 12.0,
            "Longitude": 135.0,
            "CentralPressure": "1006",
            "Maximum_sustained_wind_speed": "000"
        },
        {
            "Time": "1985-10-22T06:00:00",
            "Grade": "2",
            "Latitude": 12.5,
            "Longitude": 134.5,
            "CentralPressure": "1006",
            "Maximum_sustained_wind_speed": "000"
        },
        {
            "Time": "1985-10-22T12:00:00",
            "Grade": "2",
            "Latitude": 13.0,
            "Longitude": 134.0,
            "CentralPressure": "1006",
            "Maximum_sustained_wind_speed": "000"
        },
        {
            "Time": "1985-10-22T18:00:00",
            "Grade": "2",
            "Latitude": 13.5,
            "Longitude": 133.5,
            "CentralPressure": "1006",
            "Maximum_sustained_wind_speed": "000"
        },
        {
            "Time": "1985-10-23T00:00:00",
            "Grade": "2",
            "Latitude": 14.0,
            "Longitude": 133.0,
            "CentralPressure": "1008",
            "Maximum_sustained_wind_speed": "000"
        }
    ],
    "FirstPointDate": "1985-10-15T12:00:00"
}