{
    "International_number_ID": "9720",
    "Data_lines": "49",
    "Tropical_cyclone_number_ID": "0023",
    "International_number_ID_Replicate": "9720",
    "Flag": "1",
    "DurationOfTimeUnit": "0",
    "Name": "DAVID",
    "LastRevisionDate": "19980119",
    "Type": "9",
    "Route": [
        {
            "Time": "1997-09-11T06:00:00",
            "Grade": "2",
            "Latitude": 10.0,
            "Longitude": 170.1,
            "CentralPressure": "1000",
            "Maximum_sustained_wind_speed": "000"
        },
        {
            "Time": "1997-09-11T12:00:00",
            "Grade": "2",
            "Latitude": 11.3,
            "Longitude": 169.9,
            "CentralPressure": "1000",
            "Maximum_sustained_wind_speed": "000"
        },
        {
            "Time": "1997-09-11T18:00:00",
            "Grade": "2",
            "Latitude": 12.4,
            "Longitude": 169.8,
            "CentralPressure": "1000",
            "Maximum_sustained_wind_speed": "000"
        },
        {
            "Time": "1997-09-12T00:00:00",
            "Grade": "2",
            "Latitude": 13.2,
            "Longitude": 169.5,
            "CentralPressure": "1000",
            "Maximum_sustained_wind_speed": "000"
        },
        {
            "Time": "1997-09-12T06:00:00",
            "Grade": "2",
            "Latitude": 13.7,
            "Longitude": 168.6,
            "CentralPressure": "1000",
            "Maximum_sustained_wind_speed": "000"
        },
        {
            "Time": "1997-09-12T12:00:00",
            "Grade": "2",
            "Latitude": 14.2,
            "Longitude": 167.5,
            "CentralPressure": "998",
            "Maximum_sustained_wind_speed": "000"
        },
        {
            "Time": "1997-09-12T18:00:00",
            "Grade": "3",
            "Latitude": 14.5,
            "Longitude": 166.8,
            "CentralPressure": "994",
            "Maximum_sustained_wind_speed": "035",
            "Direction_LR50plus": "0",
            "Longest_radius_of_50kt": 0,
            "Shortest_radius_of_50kt": 0,
            "Direction_LR30plus": "9",
            "Longest_radius_of_30kt": 100,
            "Shortest_radius_of_30kt": 100
        },
        {
            "Time": "1997-09-13T00:00:00",
            "Grade": "3",
            "Latitude": 14.8,
            "Longitude": 166.0,
            "CentralPressure": "992",
            "Maximum_sustained_wind_speed": "040",
            "Direction_LR50plus": "0",
            "Longest_radius_of_50kt": 0,
            "Shortest_radius_of_50kt": 0,
            "Direction_LR30plus": "9",
            "Longest_radius_of_30kt": 100,
            "Shortest_radius_of_30kt": 100
        },
        {
            "Time": "1997-09-13T06:00:00",
            "Grade": "4",
            "Latitude": 15.1,
            "Longitude": 165.3,
            "CentralPressure": "990",
            "Maximum_sustained_wind_speed": "050",
            "Direction_LR50plus": "0",
            "Longest_radius_of_50kt": 0,
            "Shortest_radius_of_50kt": 0,
            "Direction_LR30plus": "9",
            "Longest_radius_of_30kt": 120,
            "Shortest_radius_of_30kt": 120
        },
        {
            "Time": "1997-09-13T12:00:00",
            "Grade": "4",
            "Latitude": 15.5,
            "Longitude": 164.7,
            "CentralPressure": "990",
            "Maximum_sustained_wind_speed": "050",
            "Direction_LR50plus": "0",
            "Longest_radius_of_50kt": 0,
            "Shortest_radius_of_50kt": 0,
            "Direction_LR30plus": "9",
            "Longest_radius_of_30kt": 120,
            "Shortest_radius_of_30kt": 120
        },
        {
            "Time": "1997-09-13T18:00:00",
            "Grade": "4",
            "Latitude": 15.9,
            "Longitude": 164.1,
            "CentralPressure": "985",
            "Maximum_sustained_wind_speed": "055",
            "Direction_LR50plus": "9",
            "Longest_radius_of_50kt": 40,
            "Shortest_radius_of_50kt": 40,
            "Direction_LR30plus": "9",
            "Longest_radius_of_30kt": 140,
            "Shortest_radius_of_30kt": 140
        },
        {
            "Time": "1997-09-14T00:00:00",
            "Grade": "4",
            "Latitude": 16.5,
            "Longitude": 163.5,
            "CentralPressure": "980",
            "Maximum_sustained_wind_speed": "060",
            "Direction_LR50plus": "9",
            "Longest_radius_of_50kt": 50,
            "Shortest_radius_of_50kt": 50,
            "Direction_LR30plus": "9",
            "Longest_radius_of_30kt": 160,
            "Shortest_radius_of_30kt": 160
        },
        {
            "Time": "1997-09-14T06:00:00",
            "Grade": "4",
            "Latitude": 17.8,
            "Longitude": 162.9,
            "CentralPressure": "975",
            "Maximum_sustained_wind_speed": "060",
            "Direction_LR50plus": "9",
            "Longest_radius_of_50kt": 60,
            "Shortest_radius_of_50kt": 60,
            "Direction_LR30plus": "9",
            "Longest_radius_of_30kt": 220,
            "Shortest_radius_of_30kt": 220
        },
        {
            "Time": "1997-09-14T12:00:00",
            "Grade": "5",
            "Latitude": 18.9,
            "Longitude": 162.0,
            "CentralPressure": "970",
            "Maximum_sustained_wind_speed": "065",
            "Direction_LR50plus": "9",
            "Longest_radius_of_50kt": 70,
            "Shortest_radius_of_50kt": 70,
            "Direction_LR30plus": "9",
            "Longest_radius_of_30kt": 250,
            "Shortest_radius_of_30kt": 250
        },
        {
            "Time": "1997-09-14T18:00:00",
            "Grade": "5",
            "Latitude": 20.3,
            "Longitude": 160.5,
            "CentralPressure": "965",
            "Maximum_sustained_wind_speed": "070",
            "Direction_LR50plus": "9",
            "Longest_radius_of_50kt": 80,
            "Shortest_radius_of_50kt": 80,
            "Direction_LR30plus": "9",
            "Longest_radius_of_30kt": 300,
            "Shortest_radius_of_30kt": 300
        },
        {
            "Time": "1997-09-15T00:00:00",
            "Grade": "5",
            "Latitude": 21.1,
            "Longitude": 159.0,
            "CentralPressure": "955",
            "Maximum_sustained_wind_speed": "075",
            "Direction_LR50plus": "9",
            "Longest_radius_of_50kt": 110,
            "Shortest_radius_of_50kt": 110,
            "Direction_LR30plus": "9",
            "Longest_radius_of_30kt": 350,
            "Shortest_radius_of_30kt": 350
        },
        {
            "Time": "1997-09-15T06:00:00",
            "Grade": "5",
            "Latitude": 22.0,
            "Longitude": 157.7,
            "CentralPressure": "950",
            "Maximum_sustained_wind_speed": "080",
            "Direction_LR50plus": "9",
            "Longest_radius_of_50kt": 120,
            "Shortest_radius_of_50kt": 120,
            "Direction_LR30plus": "9",
            "Longest_radius_of_30kt": 375,
            "Shortest_radius_of_30kt": 375
        },
        {
            "Time": "1997-09-15T12:00:00",
            "Grade": "5",
            "Latitude": 22.6,
            "Longitude": 156.4,
            "CentralPressure": "945",
            "Maximum_sustained_wind_speed": "085",
            "Direction_LR50plus": "9",
            "Longest_radius_of_50kt": 130,
            "Shortest_radius_of_50kt": 130,
            "Direction_LR30plus": "9",
            "Longest_radius_of_30kt": 375,
            "Shortest_radius_of_30kt": 375
        },
        {
            "Time": "1997-09-15T18:00:00",
            "Grade": "5",
            "Latitude": 23.0,
            "Longitude": 155.4,
            "CentralPressure": "945",
            "Maximum_sustained_wind_speed": "085",
            "Direction_LR50plus": "9",
            "Longest_radius_of_50kt": 130,
            "Shortest_radius_of_50kt": 130,
            "Direction_LR30plus": "9",
            "Longest_radius_of_30kt": 375,
            "Shortest_radius_of_30kt": 375
        },
        {
            "Time": "1997-09-16T00:00:00",
            "Grade": "5",
            "Latitude": 23.4,
            "Longitude": 154.0,
            "CentralPressure": "945",
            "Maximum_sustained_wind_speed": "085",
            "Direction_LR50plus": "9",
            "Longest_radius_of_50kt": 130,
            "Shortest_radius_of_50kt": 130,
            "Direction_LR30plus": "9",
            "Longest_radius_of_30kt": 375,
            "Shortest_radius_of_30kt": 375
        },
        {
            "Time": "1997-09-16T06:00:00",
            "Grade": "5",
            "Latitude": 23.9,
            "Longitude": 152.7,
            "CentralPressure": "945",
            "Maximum_sustained_wind_speed": "085",
            "Direction_LR50plus": "9",
            "Longest_radius_of_50kt": 130,
            "Shortest_radius_of_50kt": 130,
            "Direction_LR30plus": "9",
            "Longest_radius_of_30kt": 375,
            "Shortest_radius_of_30kt": 375
        },
        {
            "Time": "1997-09-16T12:00:00",
            "Grade": "5",
            "Latitude": 24.3,
            "Longitude": 151.2,
            "CentralPressure": "945",
            "Maximum_sustained_wind_speed": "085",
            "Direction_LR50plus": "9",
            "Longest_radius_of_50kt": 110,
            "Shortest_radius_of_50kt": 110,
            "Direction_LR30plus": "9",
            "Longest_radius_of_30kt": 375,
            "Shortest_radius_of_30kt": 375
        },
        {
            "Time": "1997-09-16T18:00:00",
            "Grade": "5",
            "Latitude": 24.8,
            "Longitude": 149.6,
            "CentralPressure": "950",
            "Maximum_sustained_wind_speed": "080",
            "Direction_LR50plus": "9",
            "Longest_radius_of_50kt": 100,
            "Shortest_radius_of_50kt": 100,
            "Direction_LR30plus": "9",
            "Longest_radius_of_30kt": 375,
            "Shortest_radius_of_30kt": 375
        },
        {
            "Time": "1997-09-17T00:00:00",
            "Grade": "5",
            "Latitude": 25.2,
            "Longitude": 148.0,
            "CentralPressure": "955",
            "Maximum_sustained_wind_speed": "075",
            "Direction_LR50plus": "9",
            "Longest_radius_of_50kt": 90,
            "Shortest_radius_of_50kt": 90,
            "Direction_LR30plus": "9",
            "Longest_radius_of_30kt": 375,
            "Shortest_radius_of_30kt": 375
        },
        {
            "Time": "1997-09-17T06:00:00",
            "Grade": "5",
            "Latitude": 25.8,
            "Longitude": 146.4,
            "CentralPressure": "960",
            "Maximum_sustained_wind_speed": "075",
            "Direction_LR50plus": "9",
            "Longest_radius_of_50kt": 80,
            "Shortest_radius_of_50kt": 80,
            "Direction_LR30plus": "9",
            "Longest_radius_of_30kt": 375,
            "Shortest_radius_of_30kt": 375
        },
        {
            "Time": "1997-09-17T12:00:00",
            "Grade": "5",
            "Latitude": 26.3,
            "Longitude": 145.0,
            "CentralPressure": "960",
            "Maximum_sustained_wind_speed": "075",
            "Direction_LR50plus": "9",
            "Longest_radius_of_50kt": 80,
            "Shortest_radius_of_50kt": 80,
            "Direction_LR30plus": "9",
            "Longest_radius_of_30kt": 375,
            "Shortest_radius_of_30kt": 375
        },
        {
            "Time": "1997-09-17T15:00:00",
            "Grade": "5",
            "Latitude": 26.6,
            "Longitude": 144.4,
            "CentralPressure": "960",
            "Maximum_sustained_wind_speed": "075",
            "Direction_LR50plus": "9",
            "Longest_radius_of_50kt": 80,
            "Shortest_radius_of_50kt": 80,
            "Direction_LR30plus": "9",
            "Longest_radius_of_30kt": 375,
            "Shortest_radius_of_30kt": 375
        },
        {
            "Time": "1997-09-17T18:00:00",
            "Grade": "5",
            "Latitude": 27.0,
            "Longitude": 143.6,
            "CentralPressure": "960",
            "Maximum_sustained_wind_speed": "075",
            "Direction_LR50plus": "9",
            "Longest_radius_of_50kt": 80,
            "Shortest_radius_of_50kt": 80,
            "Direction_LR30plus": "9",
            "Longest_radius_of_30kt": 375,
            "Shortest_radius_of_30kt": 375
        },
        {
            "Time": "1997-09-17T21:00:00",
            "Grade": "5",
            "Latitude": 27.4,
            "Longitude": 143.1,
            "CentralPressure": "960",
            "Maximum_sustained_wind_speed": "075",
            "Direction_LR50plus": "9",
            "Longest_radius_of_50kt": 80,
            "Shortest_radius_of_50kt": 80,
            "Direction_LR30plus": "9",
            "Longest_radius_of_30kt": 375,
            "Shortest_radius_of_30kt": 375
        },
        {
            "Time": "1997-09-18T00:00:00",
            "Grade": "5",
            "Latitude": 27.8,
            "Longitude": 142.6,
            "CentralPressure": "960",
            "Maximum_sustained_wind_speed": "075",
            "Direction_LR50plus": "9",
            "Longest_radius_of_50kt": 80,
            "Shortest_radius_of_50kt": 80,
            "Direction_LR30plus": "9",
            "Longest_radius_of_30kt": 375,
            "Shortest_radius_of_30kt": 375
        },
        {
            "Time": "1997-09-18T03:00:00",
            "Grade": "5",
            "Latitude": 28.4,
            "Longitude": 142.2,
            "CentralPressure": "960",
            "Maximum_sustained_wind_speed": "075",
            "Direction_LR50plus": "9",
            "Longest_radius_of_50kt": 80,
            "Shortest_radius_of_50kt": 80,
            "Direction_LR30plus": "9",
            "Longest_radius_of_30kt": 375,
            "Shortest_radius_of_30kt": 375
        },
        {
            "Time": "1997-09-18T06:00:00",
            "Grade": "5",
            "Latitude": 29.1,
            "Longitude": 142.0,
            "CentralPressure": "965",
            "Maximum_sustained_wind_speed": "070",
            "Direction_LR50plus": "9",
            "Longest_radius_of_50kt": 80,
            "Shortest_radius_of_50kt": 80,
            "Direction_LR30plus": "9",
            "Longest_radius_of_30kt": 375,
            "Shortest_radius_of_30kt": 375
        },
        {
            "Time": "1997-09-18T09:00:00",
            "Grade": "5",
            "Latitude": 29.8,
            "Longitude": 141.9,
            "CentralPressure": "965",
            "Maximum_sustained_wind_speed": "070",
            "Direction_LR50plus": "9",
            "Longest_radius_of_50kt": 80,
            "Shortest_radius_of_50kt": 80,
            "Direction_LR30plus": "9",
            "Longest_radius_of_30kt": 375,
            "Shortest_radius_of_30kt": 375
        },
        {
            "Time": "1997-09-18T12:00:00",
            "Grade": "5",
            "Latitude": 30.6,
            "Longitude": 141.6,
            "CentralPressure": "965",
            "Maximum_sustained_wind_speed": "070",
            "Direction_LR50plus": "9",
            "Longest_radius_of_50kt": 80,
            "Shortest_radius_of_50kt": 80,
            "Direction_LR30plus": "1",
            "Longest_radius_of_30kt": 450,
            "Shortest_radius_of_30kt": 300
        },
        {
            "Time": "1997-09-18T15:00:00",
            "Grade": "5",
            "Latitude": 31.3,
            "Longitude": 141.6,
            "CentralPressure": "965",
            "Maximum_sustained_wind_speed": "070",
            "Direction_LR50plus": "9",
            "Longest_radius_of_50kt": 80,
            "Shortest_radius_of_50kt": 80,
            "Direction_LR30plus": "1",
            "Longest_radius_of_30kt": 450,
            "Shortest_radius_of_30kt": 300
        },
        {
            "Time": "1997-09-18T18:00:00",
            "Grade": "5",
            "Latitude": 32.2,
            "Longitude": 141.6,
            "CentralPressure": "965",
            "Maximum_sustained_wind_speed": "070",
            "Direction_LR50plus": "9",
            "Longest_radius_of_50kt": 80,
            "Shortest_radius_of_50kt": 80,
            "Direction_LR30plus": "1",
            "Longest_radius_of_30kt": 450,
            "Shortest_radius_of_30kt": 300
        },
        {
            "Time": "1997-09-18T21:00:00",
            "Grade": "5",
            "Latitude": 33.2,
            "Longitude": 142.0,
            "CentralPressure": "965",
            "Maximum_sustained_wind_speed": "070",
            "Direction_LR50plus": "9",
            "Longest_radius_of_50kt": 80,
            "Shortest_radius_of_50kt": 80,
            "Direction_LR30plus": "1",
            "Longest_radius_of_30kt": 450,
            "Shortest_radius_of_30kt": 300
        },
        {
            "Time": "1997-09-19T00:00:00",
            "Grade": "5",
            "Latitude": 34.0,
            "Longitude": 142.3,
            "CentralPressure": "970",
            "Maximum_sustained_wind_speed": "065",
            "Direction_LR50plus": "9",
            "Longest_radius_of_50kt": 70,
            "Shortest_radius_of_50kt": 70,
            "Direction_LR30plus": "1",
            "Longest_radius_of_30kt": 450,
            "Shortest_radius_of_30kt": 300
        },
        {
            "Time": "1997-09-19T03:00:00",
            "Grade": "5",
            "Latitude": 35.0,
            "Longitude": 143.0,
            "CentralPressure": "970",
            "Maximum_sustained_wind_speed": "065",
            "Direction_LR50plus": "9",
            "Longest_radius_of_50kt": 70,
            "Shortest_radius_of_50kt": 70,
            "Direction_LR30plus": "1",
            "Longest_radius_of_30kt": 450,
            "Shortest_radius_of_30kt": 350
        },
        {
            "Time": "1997-09-19T06:00:00",
            "Grade": "5",
            "Latitude": 36.0,
            "Longitude": 144.0,
            "CentralPressure": "970",
            "Maximum_sustained_wind_speed": "065",
            "Direction_LR50plus": "9",
            "Longest_radius_of_50kt": 70,
            "Shortest_radius_of_50kt": 70,
            "Direction_LR30plus": "1",
            "Longest_radius_of_30kt": 450,
            "Shortest_radius_of_30kt": 350
        },
        {
            "Time": "1997-09-19T09:00:00",
            "Grade": "5",
            "Latitude": 37.3,
            "Longitude": 145.7,
            "CentralPressure": "970",
            "Maximum_sustained_wind_speed": "065",
            "Direction_LR50plus": "9",
            "Longest_radius_of_50kt": 70,
            "Shortest_radius_of_50kt": 70,
            "Direction_LR30plus": "1",
            "Longest_radius_of_30kt": 450,
            "Shortest_radius_of_30kt": 350
        },
        {
            "Time": "1997-09-19T12:00:00",
            "Grade": "4",
            "Latitude": 38.6,
            "Longitude": 147.3,
            "CentralPressure": "975",
            "Maximum_sustained_wind_speed": "060",
            "Direction_LR50plus": "9",
            "Longest_radius_of_50kt": 60,
            "Shortest_radius_of_50kt": 60,
            "Direction_LR30plus": "1",
            "Longest_radius_of_30kt": 450,
            "Shortest_radius_of_30kt": 350
        },
        {
            "Time": "1997-09-19T18:00:00",
            "Grade": "6",
            "Latitude": 41.9,
            "Longitude": 151.8,
            "CentralPressure": "976",
            "Maximum_sustained_wind_speed": "000"
        },
        {
            "Time": "1997-09-20T00:00:00",
            "Grade": "6",
            "Latitude": 46.1,
            "Longitude": 154.0,
            "CentralPressure": "972",
            "Maximum_sustained_wind_speed": "000"
        },
        {
            "Time": "1997-09-20T06:00:00",
            "Grade": "6",
            "Latitude": 48.6,
            "Longitude": 158.3,
            "CentralPressure": "968",
            "Maximum_sustained_wind_speed": "000"
        },
        {
            "Time": "1997-09-20T12:00:00",
            "Grade": "6",
            "Latitude": 49.8,
            "Longitude": 163.0,
            "CentralPressure": "964",
            "Maximum_sustained_wind_speed": "000"
        },
        {
            "Time": "1997-09-20T18:00:00",
            "Grade": "6",
            "Latitude": 50.9,
            "Longitude": 169.2,
            "CentralPressure": "960",
            "Maximum_sustained_wind_speed": "000"
        },
        {
            "Time": "1997-09-21T00:00:00",
            "Grade": "6",
            "Latitude": 50.9,
            "Longitude": 175.3,
            "CentralPressure": "960",
            "Maximum_sustained_wind_speed": "000"
        },
        {
            "Time": "1997-09-21T06:00:00",
            "Grade": "6",
            "Latitude": 51.1,
            "Longitude": 181.3,
            "CentralPressure": "964",
            "Maximum_sustained_wind_speed": "000"
        }
    ],
    "FirstPointDate": "1997-09-11T06:00:00"
}